{
  "products": [
    {
      "id": 0,
      "gender": "Чоловічі Кросівки",
      "name": "Blazer Mid Suede",
      "price": "3999 грн",
      "image": "1.jpg"
    },
    {
      "id": 1,
      "gender": "Жіночі Кросівки",
      "name": "Nike Air Max 270",
      "price": "4199 грн",
      "image": "2.jpg"
    },
    {
      "id": 2,
      "gender": "Жіночі Кросівки",
      "name": "Nike Blazer Mid Suede",
      "price": "3499 грн",
      "image": "3.jpg"
    },
    {
      "id": 3,
      "gender": "Чоловічі Кросівки",
      "name": "Puma X Aka Boku Future Rider",
      "price": "4999 грн",
      "image": "4.jpg"
    },
    {
      "id": 4,
      "gender": "Жіночі Кросівки",
      "name": "Under Armour Curry 8",
      "price": "5299 грн",
      "image": "5.jpg"
    },
    {
      "id": 5,
      "gender": "Жіночі Кросівки",
      "name": "Kyrie 7",
      "price": "3299 грн",
      "image": "6.jpg"
    },
    {
      "id": 6,
      "gender": "Чоловічі Кросівки",
      "name": "Jordan Air Jordan 11",
      "price": "3799 грн",
      "image": "7.jpg"
    },
    {
      "id": 7,
      "gender": "Чоловічі Кросівки",
      "name": "LeBron XVIII",
      "price": "4399 грн",
      "image": "8.jpg"
    },
    {
      "id": 8,
      "gender": "Чоловічі Кросівки",
      "name": "Lebron XVIII Low",
      "price": "4799 грн",
      "image": "9.jpg"
    },
    {
      "id": 9,
      "gender": "Жіночі Кросівки",
      "name": "Blazer Mid Suede",
      "price": "3999 грн",
      "image": "1.jpg"
    },
    {
      "id": 10,
      "gender": "Чоловічі Кросівки",
      "name": "Nike Kyrie Flytrap IV",
      "price": "4099 грн",
      "image": "10.jpg"
    },
    {
      "id": 11,
      "gender": "Жіночі Кросівки",
      "name": "Blazer Mid Suede",
      "price": "3499 грн",
      "image": "3.jpg"
    }
  ]
}